{
  "color": {
    "graphite-ink": {
      "$value": "#1b1b1b",
      "$type": "color",
      "$description": "Graphite Ink — Supporting neutral for secondary UI, dividers, and muted labels. Do not promote it to the primary CTA color"
    },
    "marble": {
      "$value": "#ffffff",
      "$type": "color",
      "$description": "Marble — Card surfaces, elevated panels, nav background, button text on dark fills. The brightest layer in the system"
    },
    "drafting-gray": {
      "$value": "#eaeaea",
      "$type": "color",
      "$description": "Drafting Gray — Page canvas and section backgrounds. The second surface tier beneath white cards — the tone of the drafting table itself"
    },
    "steel": {
      "$value": "#60646c",
      "$type": "color",
      "$description": "Steel — Secondary body text, subtext, helper copy. Carries information density without competing with primary headings"
    },
    "ash": {
      "$value": "#7c7c7c",
      "$type": "color",
      "$description": "Ash — Muted tertiary text and less-emphasized metadata. Used where information recedes"
    },
    "hairline": {
      "$value": "#e0e1e6",
      "$type": "color",
      "$description": "Hairline — 1px borders, card outlines, divider rules. The system's structural lines — cool-tinted to read as architectural, not decorative"
    },
    "mint-signal": {
      "$value": "#00f2e6",
      "$type": "color",
      "$description": "Mint Signal — Saturated cyan-mint used inside product UI mockups and integration icon tiles. Not an interface accent — it is product-content color bleeding into marketing surfaces"
    },
    "moss": {
      "$value": "#8dc63f",
      "$type": "color",
      "$description": "Moss — Secondary chromatic accent appearing in product screenshot data and integration tiles. Sits next to Mint Signal in the same icon/system cluster"
    },
    "sky": {
      "$value": "#00b9f1",
      "$type": "color",
      "$description": "Sky — Tertiary accent in product UI and integration iconography. Completes the cool triad (mint, moss, sky) that defines the brand's chromatic fingerprint within screenshots"
    },
    "forest-to-deep-gradient": {
      "$value": "#19a05f",
      "$type": "color",
      "$description": "Forest-to-Deep Gradient — Announcement bar gradient spanning green (#19a05f) into deep teal (#0d7f8c). Sole place the interface shows color — the only banner-style element on the site"
    }
  },
  "font": {
    "inter": {
      "$value": "Inter",
      "$type": "fontFamily",
      "$description": "Sole typeface. Display uses weight 600 at 90px with -0.05em tracking (about -4.5px) — headline authority through geometric compression rather than heaviness. Headings at 40px use weight 500 with -0.025em tracking for a slightly looser, more editorial register. Body at 16px stays at weight 400 with normal tracking. The 13/14px sizes handle UI chrome and captions. No system fonts, no second family — Inter is the brand."
    },
    "sans-custom-utility": {
      "$value": "sans (custom utility)",
      "$type": "fontFamily",
      "$description": "Rare fallback utility class. Treat as Inter — likely a Tailwind 'sans' alias that resolved to a custom stack. Do not introduce as a distinct type family in output."
    }
  },
  "typography": {
    "sm": {
      "$value": {
        "fontFamily": "Inter",
        "fontSize": "13px",
        "fontWeight": 500,
        "lineHeight": 1.5
      },
      "$type": "typography",
      "$description": "Typography step sm at 13px"
    },
    "sm-2": {
      "$value": {
        "fontFamily": "sans",
        "fontSize": "14px",
        "fontWeight": 400,
        "lineHeight": 1.43
      },
      "$type": "typography",
      "$description": "Typography step sm-2 at 14px"
    },
    "sm-3": {
      "$value": {
        "fontFamily": "sans",
        "fontSize": "14px",
        "fontWeight": 500,
        "lineHeight": 1.43
      },
      "$type": "typography",
      "$description": "Typography step sm-3 at 14px"
    },
    "sm-4": {
      "$value": {
        "fontFamily": "Inter",
        "fontSize": "14px",
        "fontWeight": 400,
        "lineHeight": 1.43
      },
      "$type": "typography",
      "$description": "Typography step sm-4 at 14px"
    },
    "sm-5": {
      "$value": {
        "fontFamily": "Inter",
        "fontSize": "14px",
        "fontWeight": 500,
        "lineHeight": 1.43
      },
      "$type": "typography",
      "$description": "Typography step sm-5 at 14px"
    },
    "sm-6": {
      "$value": {
        "fontFamily": "Inter",
        "fontSize": "14px",
        "fontWeight": 400,
        "lineHeight": 2
      },
      "$type": "typography",
      "$description": "Typography step sm-6 at 14px"
    },
    "sm-7": {
      "$value": {
        "fontFamily": "Inter",
        "fontSize": "14px",
        "fontWeight": 500,
        "lineHeight": 1.5
      },
      "$type": "typography",
      "$description": "Typography step sm-7 at 14px"
    },
    "sm-8": {
      "$value": {
        "fontFamily": "Inter",
        "fontSize": "14px",
        "fontWeight": 600,
        "lineHeight": 1.43
      },
      "$type": "typography",
      "$description": "Typography step sm-8 at 14px"
    },
    "base": {
      "$value": {
        "fontFamily": "sans",
        "fontSize": "16px",
        "fontWeight": 400,
        "lineHeight": 1.5
      },
      "$type": "typography",
      "$description": "Typography step base at 16px"
    },
    "base-2": {
      "$value": {
        "fontFamily": "Inter",
        "fontSize": "16px",
        "fontWeight": 400,
        "lineHeight": 1.5
      },
      "$type": "typography",
      "$description": "Typography step base-2 at 16px"
    },
    "base-3": {
      "$value": {
        "fontFamily": "Inter",
        "fontSize": "16px",
        "fontWeight": 500,
        "lineHeight": 1.5
      },
      "$type": "typography",
      "$description": "Typography step base-3 at 16px"
    },
    "base-4": {
      "$value": {
        "fontFamily": "Inter",
        "fontSize": "16px",
        "fontWeight": 600,
        "lineHeight": 1.1
      },
      "$type": "typography",
      "$description": "Typography step base-4 at 16px"
    },
    "xl": {
      "$value": {
        "fontFamily": "Inter",
        "fontSize": "20px",
        "fontWeight": 400,
        "lineHeight": 1.5
      },
      "$type": "typography",
      "$description": "Typography step xl at 20px"
    },
    "2xl": {
      "$value": {
        "fontFamily": "Inter",
        "fontSize": "24px",
        "fontWeight": 600,
        "lineHeight": 1.1
      },
      "$type": "typography",
      "$description": "Typography step 2xl at 24px"
    },
    "4xl": {
      "$value": {
        "fontFamily": "Inter",
        "fontSize": "40px",
        "fontWeight": 700,
        "lineHeight": 1.1
      },
      "$type": "typography",
      "$description": "Typography step 4xl at 40px"
    },
    "5xl": {
      "$value": {
        "fontFamily": "Inter",
        "fontSize": "90px",
        "fontWeight": 700,
        "lineHeight": 1
      },
      "$type": "typography",
      "$description": "Typography step 5xl at 90px"
    }
  },
  "spacing": {
    "4": {
      "$value": "4px",
      "$type": "dimension",
      "$description": "Spacing 4px"
    },
    "8": {
      "$value": "8px",
      "$type": "dimension",
      "$description": "Spacing 8px"
    },
    "12": {
      "$value": "12px",
      "$type": "dimension",
      "$description": "Spacing 12px"
    },
    "16": {
      "$value": "16px",
      "$type": "dimension",
      "$description": "Spacing 16px"
    },
    "20": {
      "$value": "20px",
      "$type": "dimension",
      "$description": "Spacing 20px"
    },
    "24": {
      "$value": "24px",
      "$type": "dimension",
      "$description": "Spacing 24px"
    },
    "28": {
      "$value": "28px",
      "$type": "dimension",
      "$description": "Spacing 28px"
    },
    "32": {
      "$value": "32px",
      "$type": "dimension",
      "$description": "Spacing 32px"
    },
    "40": {
      "$value": "40px",
      "$type": "dimension",
      "$description": "Spacing 40px"
    },
    "44": {
      "$value": "44px",
      "$type": "dimension",
      "$description": "Spacing 44px"
    },
    "48": {
      "$value": "48px",
      "$type": "dimension",
      "$description": "Spacing 48px"
    },
    "72": {
      "$value": "72px",
      "$type": "dimension",
      "$description": "Spacing 72px"
    },
    "80": {
      "$value": "80px",
      "$type": "dimension",
      "$description": "Spacing 80px"
    },
    "100": {
      "$value": "100px",
      "$type": "dimension",
      "$description": "Spacing 100px"
    },
    "128": {
      "$value": "128px",
      "$type": "dimension",
      "$description": "Spacing 128px"
    },
    "unit": {
      "$value": "4px",
      "$type": "dimension",
      "$description": "Base spacing unit"
    }
  },
  "radius": {
    "md": {
      "$value": "6px",
      "$type": "dimension",
      "$description": "Border radius md"
    },
    "xl": {
      "$value": "12px",
      "$type": "dimension",
      "$description": "Border radius xl"
    },
    "2xl": {
      "$value": "20px",
      "$type": "dimension",
      "$description": "Border radius 2xl"
    },
    "3xl": {
      "$value": "40px",
      "$type": "dimension",
      "$description": "Border radius 3xl"
    }
  },
  "shadow": {
    "lg": {
      "$value": "rgba(0, 0, 0, 0.15) 0px 4px 20px 0px",
      "$type": "shadow",
      "$description": "Shadow elevation lg"
    }
  },
  "surface": {
    "canvas": {
      "$value": "#eaeaea",
      "$type": "color",
      "$description": "Surface level 1: Page background — the drafting table."
    },
    "card": {
      "$value": "#ffffff",
      "$type": "color",
      "$description": "Surface level 2: All content surfaces: feature cards, nav bar, CTA containers, product mockups."
    },
    "elevated": {
      "$value": "#ffffff",
      "$type": "color",
      "$description": "Surface level 3: Modals, popovers, and the dashboard preview — same white as Card, distinguished by shadow and z-index, not by a new color."
    }
  },
  "$extensions": {}
}