{
  "color": {
    "midnight-ink": {
      "$value": "#091135",
      "$type": "color",
      "$description": "Midnight Ink — Primary text, headings, nav, body, link color — the dominant ink of the entire interface, set against white and pale-lavender surfaces"
    },
    "electric-blue": {
      "$value": "#0f77ff",
      "$type": "color",
      "$description": "Electric Blue — Blue outline accent for tags, dividers, and focused UI edges. Do not promote it to the primary CTA color"
    },
    "cobalt-surface": {
      "$value": "#127ee3",
      "$type": "color",
      "$description": "Cobalt Surface — Blue wash for highlight backgrounds, decorative bands, and soft emphasis behind content. Do not promote it to the primary CTA color"
    },
    "slate": {
      "$value": "#36394a",
      "$type": "color",
      "$description": "Slate — Secondary muted text where Midnight Ink would be too heavy — metadata, timestamps, helper copy"
    },
    "frost-border": {
      "$value": "#e1e9f0",
      "$type": "color",
      "$description": "Frost Border — Hairline borders on cards, inputs, dividers, and table edges — the structural line color of the entire system"
    },
    "mist": {
      "$value": "#b1bbcd",
      "$type": "color",
      "$description": "Mist — Soft shadow tone and secondary neutral — used in focus glows and deeper dividers"
    },
    "graphite": {
      "$value": "#000000",
      "$type": "color",
      "$description": "Graphite — Icon fills, deep dividers, and absolute-dark accents — used sparingly where Midnight Ink still feels too soft"
    },
    "paper": {
      "$value": "#ffffff",
      "$type": "color",
      "$description": "Paper — Page canvas, card surfaces on tinted sections, text on dark buttons"
    },
    "lavender-wash": {
      "$value": "#f5f3ff",
      "$type": "color",
      "$description": "Lavender Wash — Section background tint that signals content zones — the softest product-surface elevation above the white canvas"
    }
  },
  "font": {
    "intervar": {
      "$value": "InterVar",
      "$type": "fontFamily",
      "$description": "Sole typeface — used for nav, body, buttons, headings, everything. The signature is its tracking behavior: positive letter-spacing that widens with size (0.004em body → 0.018em display), giving large headlines a slightly diffused, architectural feel rather than the dense negative-tracked look of typical SaaS displays."
    }
  },
  "typography": {
    "sm": {
      "$value": {
        "fontFamily": "InterVar",
        "fontSize": "14px",
        "fontWeight": 500,
        "lineHeight": 1.43
      },
      "$type": "typography",
      "$description": "Typography step sm at 14px"
    },
    "sm-2": {
      "$value": {
        "fontFamily": "InterVar",
        "fontSize": "14px",
        "fontWeight": 500,
        "lineHeight": 1.25
      },
      "$type": "typography",
      "$description": "Typography step sm-2 at 14px"
    },
    "sm-3": {
      "$value": {
        "fontFamily": "InterVar",
        "fontSize": "14px",
        "fontWeight": 400,
        "lineHeight": 1.5
      },
      "$type": "typography",
      "$description": "Typography step sm-3 at 14px"
    },
    "sm-4": {
      "$value": {
        "fontFamily": "InterVar",
        "fontSize": "14px",
        "fontWeight": 400,
        "lineHeight": 1.5
      },
      "$type": "typography",
      "$description": "Typography step sm-4 at 14px"
    },
    "base": {
      "$value": {
        "fontFamily": "InterVar",
        "fontSize": "16px",
        "fontWeight": 400,
        "lineHeight": 1.5
      },
      "$type": "typography",
      "$description": "Typography step base at 16px"
    },
    "base-2": {
      "$value": {
        "fontFamily": "InterVar",
        "fontSize": "16px",
        "fontWeight": 500,
        "lineHeight": 1.5
      },
      "$type": "typography",
      "$description": "Typography step base-2 at 16px"
    },
    "base-3": {
      "$value": {
        "fontFamily": "InterVar",
        "fontSize": "16px",
        "fontWeight": 700,
        "lineHeight": 1.5
      },
      "$type": "typography",
      "$description": "Typography step base-3 at 16px"
    },
    "lg": {
      "$value": {
        "fontFamily": "InterVar",
        "fontSize": "18px",
        "fontWeight": 400,
        "lineHeight": 1.5
      },
      "$type": "typography",
      "$description": "Typography step lg at 18px"
    },
    "3xl": {
      "$value": {
        "fontFamily": "InterVar",
        "fontSize": "32px",
        "fontWeight": 600,
        "lineHeight": 1.25
      },
      "$type": "typography",
      "$description": "Typography step 3xl at 32px"
    },
    "5xl": {
      "$value": {
        "fontFamily": "InterVar",
        "fontSize": "56px",
        "fontWeight": 600,
        "lineHeight": 1.25
      },
      "$type": "typography",
      "$description": "Typography step 5xl at 56px"
    },
    "5xl-2": {
      "$value": {
        "fontFamily": "InterVar",
        "fontSize": "64px",
        "fontWeight": 600,
        "lineHeight": 1.25
      },
      "$type": "typography",
      "$description": "Typography step 5xl-2 at 64px"
    }
  },
  "spacing": {
    "8": {
      "$value": "8px",
      "$type": "dimension",
      "$description": "Spacing 8px"
    },
    "16": {
      "$value": "16px",
      "$type": "dimension",
      "$description": "Spacing 16px"
    },
    "20": {
      "$value": "20px",
      "$type": "dimension",
      "$description": "Spacing 20px"
    },
    "24": {
      "$value": "24px",
      "$type": "dimension",
      "$description": "Spacing 24px"
    },
    "32": {
      "$value": "32px",
      "$type": "dimension",
      "$description": "Spacing 32px"
    },
    "44": {
      "$value": "44px",
      "$type": "dimension",
      "$description": "Spacing 44px"
    },
    "48": {
      "$value": "48px",
      "$type": "dimension",
      "$description": "Spacing 48px"
    },
    "64": {
      "$value": "64px",
      "$type": "dimension",
      "$description": "Spacing 64px"
    },
    "80": {
      "$value": "80px",
      "$type": "dimension",
      "$description": "Spacing 80px"
    },
    "128": {
      "$value": "128px",
      "$type": "dimension",
      "$description": "Spacing 128px"
    },
    "unit": {
      "$value": "4px",
      "$type": "dimension",
      "$description": "Base spacing unit"
    }
  },
  "radius": {
    "lg": {
      "$value": "8px",
      "$type": "dimension",
      "$description": "Border radius lg"
    },
    "xl": {
      "$value": "12px",
      "$type": "dimension",
      "$description": "Border radius xl"
    },
    "3xl": {
      "$value": "24px",
      "$type": "dimension",
      "$description": "Border radius 3xl"
    }
  },
  "shadow": {
    "subtle": {
      "$value": "rgb(15, 119, 255) 0px 0px 0px 1px, rgba(12, 43, 100, 0.32) 0px 1px 2px 0px, rgba(12, 43, 100, 0.32) 0px 6px 16px 0px",
      "$type": "shadow",
      "$description": "Shadow elevation subtle"
    }
  },
  "surface": {
    "paper": {
      "$value": "#ffffff",
      "$type": "color",
      "$description": "Surface level 0: Page canvas, default body background"
    },
    "lavender-wash": {
      "$value": "#f5f3ff",
      "$type": "color",
      "$description": "Surface level 1: Section background tint for product showcase zones"
    },
    "card": {
      "$value": "#ffffff",
      "$type": "color",
      "$description": "Surface level 2: Product cards and data record surfaces floating over the lavender wash"
    },
    "cobalt-surface": {
      "$value": "#127ee3",
      "$type": "color",
      "$description": "Surface level 3: Primary action button fill"
    }
  },
  "$extensions": {}
}